hellofire/__init__.py
hellofire/project.py
hellofire-2.0.dist-info/METADATA
hellofire-2.0.dist-info/WHEEL
hellofire-2.0.dist-info/top_level.txt
hellofire-2.0.dist-info/RECORD
