Metadata-Version: 2.1
Name: hellofire
Version: 2.0
Summary: Prints🔥🔥
